deployfish_mysql/__init__.py
deployfish_mysql/hooks.py
deployfish_mysql/adapters/__init__.py
deployfish_mysql/adapters/deployfish/__init__.py
deployfish_mysql/adapters/deployfish/mysql.py
deployfish_mysql/controllers/__init__.py
deployfish_mysql/controllers/mysql.py
deployfish_mysql/models/__init__.py
deployfish_mysql/models/mysql.py
deployfish_mysql/templates/__init__.py
deployfish_mysql/templates/detail--mysqldatabase.jinja2
deployfish_mysql-1.2.16.dist-info/AUTHORS.txt
deployfish_mysql-1.2.16.dist-info/LICENSE.txt
deployfish_mysql-1.2.16.dist-info/METADATA
deployfish_mysql-1.2.16.dist-info/WHEEL
deployfish_mysql-1.2.16.dist-info/entry_points.txt
deployfish_mysql-1.2.16.dist-info/top_level.txt
deployfish_mysql-1.2.16.dist-info/RECORD
