Metadata-Version: 2.1
Name: deployfish-mysql
Version: 1.2.16
Summary: Deployfish MySQL plugin
Home-page: https://github.com/caltechads/deployfish-mysql
Author: Caltech IMSS ADS
Author-email: imss-ads-staff@caltech.edu
Project-URL: Source, https://github.com/caltechads/deployfish-mysql
Project-URL: Issues, https://github.com/caltechads/deployfish-mysql/issues
Keywords: aws,ecs,docker,devops,mysql
Classifier: Environment :: Console
Classifier: Environment :: Plugins
Classifier: Development Status :: 5 - Production/Stable
Classifier: Programming Language :: Python :: 3
Classifier: Programming Language :: Python :: 3.7
Classifier: Programming Language :: Python :: 3.8
Classifier: Programming Language :: Python :: 3.9
Classifier: Programming Language :: Python :: 3.10
Classifier: Programming Language :: Python :: 3.11
Classifier: Topic :: Database
Classifier: Topic :: System :: Installation/Setup
Classifier: Topic :: System :: Systems Administration
Requires-Python: >=3.7
License-File: LICENSE.txt
License-File: AUTHORS.txt
Requires-Dist: deployfish >=1.11.2
Requires-Dist: click >=7.0
Requires-Dist: cement >=3.0
